[
  {
    "id": "board-books-0-2",
    "title": "Board Books",
    "subtitle": "First books for tiny hands",
    "ageBadge": "0-2",
    "ageOrder": 0,
    "genre": "board",
    "genreLabel": "Board books",
    "accent": "#FFB5A7",
    "icon": "🍼",
    "pdf": null,
    "browseUrl": "https://bukmuk.com/bukmuk/browse?tags=Must%20read%20board%20books&page=1&limit=24",
    "books": [
      { "title": "Good Night Moon" },
      { "title": "Llama Llama Red Pyjama and series" },
      { "title": "Chicka Chicka Boom Boom" },
      { "title": "Press Here" },
      { "title": "Dear Zoo" },
      { "title": "Where Is Baby's Belly Button" },
      { "title": "Hands Are Not For Hitting" },
      { "title": "Where's Spot?" },
      { "title": "My First Shloka Book — Ganesha and series" },
      { "title": "Tales from Acorn Wood series", "author": "Julia Donaldson" },
      { "title": "Panda Bear, Panda Bear, What Do You See?" },
      { "title": "Peppa Pig: Peppa and her Golden Boots" },
      { "title": "Hugless Douglas" },
      { "title": "The Lion Inside (Board Book)" },
      { "title": "Monkey and Me" },
      { "title": "Pop Up Peekaboo series" },
      { "title": "Elmer (Board Book)" },
      { "title": "The Very Busy Spider" },
      { "title": "Ladybird Baby Touch series" }
    ]
  },
  {
    "id": "early-chapter-7-plus",
    "title": "Early Chapter Books",
    "subtitle": "Easy novels with lots of pictures",
    "ageBadge": "7+",
    "ageOrder": 7,
    "genre": "early-chapter",
    "genreLabel": "Early chapter",
    "accent": "#FF6B6B",
    "icon": "📖",
    "pdf": "book_recommendations/Age 7+ Early chapter fun books BUKMUK Recommendations.pdf",
    "browseUrl": "https://bukmuk.com/bukmuk/browse?tags=Must%20read%20early%20chapter%20books&page=1&limit=24",
    "books": [
      { "title": "Banana series", "count": "20+ books" },
      { "title": "Walker series", "count": "10 books" },
      { "title": "Pets Rule series", "count": "9 books" },
      { "title": "Diary of a Pug series", "count": "16 books" },
      { "title": "Fly Guy series", "count": "11 books" },
      { "title": "Dragon Masters series", "count": "18 books" },
      { "title": "Pizza and Taco series", "count": "24 books" },
      { "title": "Unicorn and Yeti series", "count": "9 books" },
      { "title": "Acorn series", "count": "20 books" },
      { "title": "Mercy Watson series", "count": "7 books" },
      { "title": "Hook Books by Penguin series", "count": "11+ books" },
      { "title": "Dreamer series", "count": "10+ books" },
      { "title": "Ivy and Bean series", "count": "12 books" },
      { "title": "Heidi Heckleberg series", "count": "10+ books" },
      { "title": "Hole Books series", "count": "20+ books" },
      { "title": "Unicorn Diaries series", "count": "33 books" },
      { "title": "Owl Diaries series", "count": "14 books" },
      { "title": "Katie Woo series", "count": "7+ books" },
      { "title": "Critters Club series", "count": "15 books" },
      { "title": "Ella Diaries series", "count": "20+ books" },
      { "title": "Rainbow Magic series", "count": "20+ books" },
      { "title": "Cupcake Diaries series", "count": "15 books" },
      { "title": "Amelia Bedelia series", "count": "6+ books" },
      { "title": "Dragon Girls series", "count": "13 books" },
      { "title": "Gulgul series", "count": "21 books" },
      { "title": "Silly Billy series", "count": "6 books" },
      { "title": "Princess in Black series", "count": "11 books" },
      { "title": "Dragon Princess series" },
      { "title": "Junie B. Jones series", "count": "20+ books" },
      { "title": "Mac B Spy series", "count": "10+ books" },
      { "title": "Ninja Kid series", "count": "7 books" },
      { "title": "Yeti Files series" },
      { "title": "Wishing Chair series", "author": "Enid Blyton", "count": "6 books" },
      { "title": "Nancy Drew and the Clue Crew", "count": "25+ books" },
      { "title": "Grimmtastic series", "count": "7 books" },
      { "title": "The Rescue Princesses series", "count": "7 books" },
      { "title": "Happy Days series", "author": "Enid Blyton", "count": "7 books" },
      { "title": "Fun in Devlok series", "count": "7 books" },
      { "title": "Tara series", "count": "5 books" },
      { "title": "Taranauts series", "count": "8 books" },
      { "title": "Investigators series", "count": "11 books" },
      { "title": "Agents of S.U.I.T series", "count": "4 books" },
      { "title": "Tom Gates series", "count": "23 books" },
      { "title": "Wimpy Kid series", "count": "21 books" },
      { "title": "Cat on the Run series", "count": "14 books" },
      { "title": "Dog Man series" },
      { "title": "Geronimo Stilton series", "count": "300+ books" },
      { "title": "Bad Guys series", "count": "20 books" },
      { "title": "Ready Freddy series" },
      { "title": "Mr Majeika series" },
      { "title": "Magic Tree House series" },
      { "title": "Flat Stanley series" },
      { "title": "Horrid Henry series" },
      { "title": "Press Start series" },
      { "title": "Minecraft series" },
      { "title": "Nate the Great series" },
      { "title": "My Weird School series" },
      { "title": "A to Z Mysteries series" },
      { "title": "Greetings from Somewhere series" },
      { "title": "Enid Blyton Star Reads", "count": "12 books" },
      { "title": "Secret Seven series", "count": "18 books" }
    ]
  },
  {
    "id": "chapter-books-9-plus",
    "title": "Chapter Books for Independent Readers",
    "subtitle": "Bigger stories, fewer pictures",
    "ageBadge": "9+",
    "ageOrder": 9,
    "genre": "chapter",
    "genreLabel": "Chapter books",
    "accent": "#6C5CE7",
    "icon": "🗝️",
    "pdf": null,
    "browseUrl": "https://bukmuk.com/bukmuk/browse?genre=Chapter%20books%20(beginner)&page=5&limit=24",
    "books": [
      { "title": "I Survived series" },
      { "title": "Land of Stories series" },
      { "title": "Andrew Clements books" },
      { "title": "Ross Welford books" },
      { "title": "David Baddiel books" },
      { "title": "Lottie Brooks books" },
      { "title": "Katherine Applegate books" },
      { "title": "Hannah Gold books" },
      { "title": "Lord of the Rings series" },
      { "title": "Harry Potter series" },
      { "title": "Percy Jackson series" },
      { "title": "Michael Morpurgo books" },
      { "title": "Storey Treehouse series" },
      { "title": "Adventure series", "author": "Enid Blyton" },
      { "title": "Middle School series" },
      { "title": "Sherlock Holmes (easy classics)" },
      { "title": "Agatha Oddly series" },
      { "title": "Mysterious Benedict Society" },
      { "title": "Aru Shah series" },
      { "title": "Strangeworld series" },
      { "title": "Holly Webb series" },
      { "title": "39 Clues series" },
      { "title": "Mr Lemoncello's Library series" },
      { "title": "Nancy Drew" },
      { "title": "Hardy Boys" },
      { "title": "Horrible Histories series" }
    ]
  },
  {
    "id": "graphic-novels",
    "title": "Comics & Graphic Novels",
    "subtitle": "Stories with pictures on every page",
    "ageBadge": "6+",
    "ageOrder": 6,
    "genre": "graphic",
    "genreLabel": "Graphic novels",
    "accent": "#4ECDC4",
    "icon": "💥",
    "pdf": "book_recommendations/Graphics Novels BUKMUK recommendations.pdf",
    "browseUrl": "https://bukmuk.com/bukmuk/browse?genre=Comics%2FGraphic%20novels&page=1&limit=24",
    "books": [
      { "title": "Dog Man", "count": "13 books" },
      { "title": "Investigators", "count": "15+ books" },
      { "title": "David Walliams", "count": "8 books" },
      { "title": "Cat Kid", "count": "8 books" },
      { "title": "Ninja Kid", "count": "18 books" },
      { "title": "Pizza and Taco series", "count": "20+ books" },
      { "title": "Press Start series", "count": "7 books" },
      { "title": "Tintin", "count": "15+ books" },
      { "title": "Asterix", "count": "20+ books" },
      { "title": "Amulet", "count": "9 books" },
      { "title": "Minecraft series" },
      { "title": "Sochu n Feelu", "count": "13 books" },
      { "title": "Trubuddy series", "count": "30+ books" },
      { "title": "Shikari Shambhu", "count": "9 books" },
      { "title": "Suppandi", "count": "25+ books" },
      { "title": "Tantri Mantri", "count": "8 books" },
      { "title": "Weirdo", "count": "7 books" },
      { "title": "Cat on the Run series", "count": "3 books" },
      { "title": "Tom Gates", "count": "24 books" },
      { "title": "Wimpy Kid", "count": "19 books" },
      { "title": "Bad Guys", "count": "20+ books" },
      { "title": "Bone series", "count": "10+ books" },
      { "title": "Baby-Sitters Club Graphix", "count": "15+ books" },
      { "title": "Baby-Sitters Little Sister Graphix", "count": "5 books" },
      { "title": "Percy Jackson Graphix", "count": "2 books" },
      { "title": "One Piece & other Manga series", "count": "30+ books" }
    ]
  }
]
